im_task_flask/__init__.py
im_task_flask-0.1.1.dist-info/DESCRIPTION.rst
im_task_flask-0.1.1.dist-info/METADATA
im_task_flask-0.1.1.dist-info/RECORD
im_task_flask-0.1.1.dist-info/WHEEL
im_task_flask-0.1.1.dist-info/metadata.json
im_task_flask-0.1.1.dist-info/top_level.txt
